claude_cache_savings/__init__.py
claude_cache_savings/__main__.py
claude_cache_savings/cli.py
claude_cache_savings/config.py
claude_cache_savings/domain.py
claude_cache_savings-0.1.0.dist-info/METADATA
claude_cache_savings-0.1.0.dist-info/WHEEL
claude_cache_savings-0.1.0.dist-info/entry_points.txt
claude_cache_savings-0.1.0.dist-info/RECORD
