Metadata-Version: 2.3
Name: claude-cache-savings
Version: 0.1.0
Summary: Calculates Anthropic Claude cost savings from use of prompt caching
License: MIT
Keywords: Athropic,Claude,Cost,Cache,Caching,Price,Usage,Statistics,Stats
Author: jojje
Author-email: tinjon+pypi@gmail.com
Requires-Python: >=3.10,<4.0
Classifier: Development Status :: 4 - Beta
Classifier: Intended Audience :: End Users/Desktop
Classifier: Topic :: Utilities
Classifier: License :: OSI Approved :: MIT License
Classifier: Operating System :: POSIX :: Linux
Classifier: Operating System :: MacOS
Classifier: Operating System :: Microsoft :: Windows
Project-URL: Homepage, https://github.com/jojje/claude-cache-savings
Project-URL: Issues, https://github.com/jojje/claude-cache-savings/issues
Project-URL: Repository, https://github.com/jojje/claude-cache-savings
